{"ongoing_trials": {}, "hyperparameters": {"space": [{"class_name": "Int", "config": {"name": "units_1", "default": null, "conditions": [], "min_value": 32, "max_value": 128, "step": 8, "sampling": "linear"}}, {"class_name": "Int", "config": {"name": "units_2", "default": null, "conditions": [], "min_value": 32, "max_value": 128, "step": 8, "sampling": "linear"}}, {"class_name": "Float", "config": {"name": "dropout", "default": 0.0, "conditions": [], "min_value": 0.0, "max_value": 0.5, "step": 0.1, "sampling": "linear"}}, {"class_name": "Choice", "config": {"name": "learning_rate", "default": 0.01, "conditions": [], "values": [0.01, 0.001, 0.0001], "ordered": true}}, {"class_name": "Int", "config": {"name": "epochs", "default": null, "conditions": [], "min_value": 50, "max_value": 200, "step": 50, "sampling": "linear"}}], "values": {"units_1": 32, "units_2": 32, "dropout": 0.0, "learning_rate": 0.01, "epochs": 50}}, "start_order": ["0", "1", "2", "3", "4"], "end_order": ["0", "1", "2", "3", "4"], "run_times": {"0": 1, "1": 1, "2": 1, "3": 1, "4": 1}, "retry_queue": [], "seed": 5926, "seed_state": 5951, "tried_so_far": ["2c77fdcd4bb5389ea057dcccfd6a7ea2", "8e6a2e189cf8f8c9c707a1e714775fd0", "6b77ebc5836c7b4c9630bb8c7ddc0773", "1dcb70ec0171e1d41b08d4316126fb23", "d434ceab66160251880a0037788213e7"], "id_to_hash": {"0": "2c77fdcd4bb5389ea057dcccfd6a7ea2", "1": "6b77ebc5836c7b4c9630bb8c7ddc0773", "2": "8e6a2e189cf8f8c9c707a1e714775fd0", "3": "1dcb70ec0171e1d41b08d4316126fb23", "4": "d434ceab66160251880a0037788213e7"}, "display": {"search_start": "2025-03-03T21:56:52.011567", "trial_start": {"0": "2025-03-03T21:56:52.011567", "1": "2025-03-03T22:24:34.312530", "2": "2025-03-03T22:56:29.523698", "3": "2025-03-03T23:14:46.477744", "4": "2025-03-03T23:44:03.266910"}, "trial_number": {"0": 1, "1": 2, "2": 3, "3": 4, "4": 5}}}